pywdrwetter/__init__.py
pywdrwetter/main.py
pywdrwetter-0.2.0.dist-info/entry_points.txt
pywdrwetter-0.2.0.dist-info/LICENSE
pywdrwetter-0.2.0.dist-info/WHEEL
pywdrwetter-0.2.0.dist-info/METADATA
pywdrwetter-0.2.0.dist-info/RECORD
